pcap.so
pypcap-1.1.4.1.dist-info/DESCRIPTION.rst
pypcap-1.1.4.1.dist-info/METADATA
pypcap-1.1.4.1.dist-info/RECORD
pypcap-1.1.4.1.dist-info/WHEEL
pypcap-1.1.4.1.dist-info/metadata.json
pypcap-1.1.4.1.dist-info/top_level.txt
