Metadata-Version: 2.0
Name: pypcap
Version: 1.1.4.1
Summary: packet capture library
Home-page: https://github.com/pynetwork/pypcap
Author: Dug Song
Author-email: dugsong@monkey.org
License: UNKNOWN
Platform: UNKNOWN
